.coveragerc
AUTHORS
CHANGELOG.txt
DESCRIPTION
LICENSE
MANIFEST.in
Makefile
README.rst
manage.py
setup.cfg
setup.py
test_requirements.txt
people/__init__.py
people/__init__.pyc
people/__init__.py~
people/admin.py
people/admin.pyc
people/models.py
people/models.pyc
people/migrations/0001_initial.py
people/migrations/0001_initial.pyc
people/migrations/0002_remove_person_full_name.py
people/migrations/0003_alter_person_nationality.py
people/migrations/0004_auto_20150923_1208.py
people/migrations/0005_auto_20150924_1044.py
people/migrations/__init__.py
people/migrations/__init__.pyc
people/settings/__init__.py
people/settings/__init__.pyc
people/settings/sphinx_documentation.py
people/settings/test_settings.py
people/settings/test_settings.pyc
people/tests/__init__.py
people/tests/__init__.pyc
people/tests/models_tests.py
people/tests/models_tests.pyc
people/tests/runtests.py
people/tests/runtests.pyc
people/tests/coverage/coverage_status.png
people/tests/coverage/excludes.html
people/tests/coverage/index.html
people/tests/coverage/modules/people.__init__.html
people/tests/coverage/modules/people.models.html
valuehorizon_people.egg-info/PKG-INFO
valuehorizon_people.egg-info/SOURCES.txt
valuehorizon_people.egg-info/dependency_links.txt
valuehorizon_people.egg-info/requires.txt
valuehorizon_people.egg-info/top_level.txt