Metadata-Version: 1.0
Name: valuehorizon-people
Version: 0.2
Summary: A Django-based People data toolkit. Part of the Valuehorizon application ecosystem.
